{
  "paper_id": "PMC10844470",
  "url": "https://www.ncbi.nlm.nih.gov/pmc/articles/PMC10844470/",
  "figures": {
    "figure_1": {
      "figure_number": "Figure 1",
      "title": "Fig. 1.",
      "caption": "Mean Acceptance of Sugar Relationships in Young Women and Men Scale by subregion. The darker shade indicates higher scores (white areas indicate a lack of data for a given region). Note: Colored figures available in electronic version only",
      "possible_urls": [
        [
          "original_src",
          "https://cdn.ncbi.nlm.nih.gov/pmc/blobs/b049/10844470/da0b272ea080/10508_2023_2724_Fig1_HTML.jpg"
        ],
        [
          "large_size",
          "https://cdn.ncbi.nlm.nih.gov/pmc/blobs/b049/10844470/da0b272ea080/10508_2023_2724_Fig1_HTML.jpg?maxwidth=2000"
        ],
        [
          "original_size",
          "https://cdn.ncbi.nlm.nih.gov/pmc/blobs/b049/10844470/da0b272ea080/10508_2023_2724_Fig1_HTML.jpg?size=original"
        ],
        [
          "xlarge_size",
          "https://cdn.ncbi.nlm.nih.gov/pmc/blobs/b049/10844470/da0b272ea080/10508_2023_2724_Fig1_HTML.jpg?maxwidth=4000"
        ]
      ],
      "figure_id": "Fig1",
      "is_table": false,
      "working_url": "https://cdn.ncbi.nlm.nih.gov/pmc/blobs/b049/10844470/da0b272ea080/10508_2023_2724_Fig1_HTML.jpg",
      "download_success": true,
      "local_image_path": "./data/PMC10844470/images/figure_1.jpg",
      "final_url": "https://cdn.ncbi.nlm.nih.gov/pmc/blobs/b049/10844470/da0b272ea080/10508_2023_2724_Fig1_HTML.jpg"
    },
    "figure_2": {
      "figure_number": "Figure 2",
      "title": "Fig. 2.",
      "caption": "Mean Acceptance of Sugar Relationships in Older Women and Men Scale by subregion. The darker shade indicates higher scores (white areas indicate a lack of data for a given region). Note: Colored figures available in electronic version only",
      "possible_urls": [
        [
          "original_src",
          "https://cdn.ncbi.nlm.nih.gov/pmc/blobs/b049/10844470/e3abea6990f6/10508_2023_2724_Fig2_HTML.jpg"
        ],
        [
          "large_size",
          "https://cdn.ncbi.nlm.nih.gov/pmc/blobs/b049/10844470/e3abea6990f6/10508_2023_2724_Fig2_HTML.jpg?maxwidth=2000"
        ],
        [
          "original_size",
          "https://cdn.ncbi.nlm.nih.gov/pmc/blobs/b049/10844470/e3abea6990f6/10508_2023_2724_Fig2_HTML.jpg?size=original"
        ],
        [
          "xlarge_size",
          "https://cdn.ncbi.nlm.nih.gov/pmc/blobs/b049/10844470/e3abea6990f6/10508_2023_2724_Fig2_HTML.jpg?maxwidth=4000"
        ]
      ],
      "figure_id": "Fig2",
      "is_table": false,
      "working_url": "https://cdn.ncbi.nlm.nih.gov/pmc/blobs/b049/10844470/e3abea6990f6/10508_2023_2724_Fig2_HTML.jpg",
      "download_success": true,
      "local_image_path": "./data/PMC10844470/images/figure_2.jpg",
      "final_url": "https://cdn.ncbi.nlm.nih.gov/pmc/blobs/b049/10844470/e3abea6990f6/10508_2023_2724_Fig2_HTML.jpg"
    },
    "figure_3": {
      "figure_number": "Figure 3",
      "title": "Fig. 3.",
      "caption": "Cross-subregional differences between ASR-YWMS and ASR-OMWS. Note: Each cell demonstrates the Cohen’s d value resulting from each pair of comparison. Upper diagonal: comparisons of the ASR-YWMS. Lower diagonal: comparisons of the ASR-OWMS",
      "possible_urls": [
        [
          "original_src",
          "https://cdn.ncbi.nlm.nih.gov/pmc/blobs/b049/10844470/56a30b16f3e3/10508_2023_2724_Fig3_HTML.jpg"
        ],
        [
          "large_size",
          "https://cdn.ncbi.nlm.nih.gov/pmc/blobs/b049/10844470/56a30b16f3e3/10508_2023_2724_Fig3_HTML.jpg?maxwidth=2000"
        ],
        [
          "original_size",
          "https://cdn.ncbi.nlm.nih.gov/pmc/blobs/b049/10844470/56a30b16f3e3/10508_2023_2724_Fig3_HTML.jpg?size=original"
        ],
        [
          "xlarge_size",
          "https://cdn.ncbi.nlm.nih.gov/pmc/blobs/b049/10844470/56a30b16f3e3/10508_2023_2724_Fig3_HTML.jpg?maxwidth=4000"
        ]
      ],
      "figure_id": "Fig3",
      "is_table": false,
      "working_url": "https://cdn.ncbi.nlm.nih.gov/pmc/blobs/b049/10844470/56a30b16f3e3/10508_2023_2724_Fig3_HTML.jpg",
      "download_success": true,
      "local_image_path": "./data/PMC10844470/images/figure_3.jpg",
      "final_url": "https://cdn.ncbi.nlm.nih.gov/pmc/blobs/b049/10844470/56a30b16f3e3/10508_2023_2724_Fig3_HTML.jpg"
    },
    "figure_4": {
      "figure_number": "Figure 4",
      "title": "Fig. 4.",
      "caption": "Cohen’s d of (ASR-YWMS—ASR-OMWS) within each subregion (white areas indicate a lack of data for a given region). Note: Colored figures available in electronic version only",
      "possible_urls": [
        [
          "original_src",
          "https://cdn.ncbi.nlm.nih.gov/pmc/blobs/b049/10844470/c5c0b12e4a1b/10508_2023_2724_Fig4_HTML.jpg"
        ],
        [
          "large_size",
          "https://cdn.ncbi.nlm.nih.gov/pmc/blobs/b049/10844470/c5c0b12e4a1b/10508_2023_2724_Fig4_HTML.jpg?maxwidth=2000"
        ],
        [
          "original_size",
          "https://cdn.ncbi.nlm.nih.gov/pmc/blobs/b049/10844470/c5c0b12e4a1b/10508_2023_2724_Fig4_HTML.jpg?size=original"
        ],
        [
          "xlarge_size",
          "https://cdn.ncbi.nlm.nih.gov/pmc/blobs/b049/10844470/c5c0b12e4a1b/10508_2023_2724_Fig4_HTML.jpg?maxwidth=4000"
        ]
      ],
      "figure_id": "Fig4",
      "is_table": false,
      "working_url": "https://cdn.ncbi.nlm.nih.gov/pmc/blobs/b049/10844470/c5c0b12e4a1b/10508_2023_2724_Fig4_HTML.jpg",
      "download_success": true,
      "local_image_path": "./data/PMC10844470/images/figure_4.jpg",
      "final_url": "https://cdn.ncbi.nlm.nih.gov/pmc/blobs/b049/10844470/c5c0b12e4a1b/10508_2023_2724_Fig4_HTML.jpg"
    }
  },
  "claims": [
    {
      "sentence": "The result of the post hoc analysis is reported in the upper diagonal of Fig. 3.",
      "figure_references": [
        {
          "figure_number": "Figure 3",
          "panel": "",
          "figure_key": "figure_3"
        }
      ]
    },
    {
      "sentence": "The result from the post hoc test is demonstrated in the lower diagonal of Fig. 3.Intra-Subregional Comparison Between the Acceptance of Receiving versus Giving Sugar Relationships (H3.3)\nWe compared the ASR-YWMS and ASR-OMWS in each subregion.",
      "figure_references": [
        {
          "figure_number": "Figure 3",
          "panel": "",
          "figure_key": "figure_3"
        }
      ]
    },
    {
      "sentence": "The comparison results are visualized in Fig. 4.",
      "figure_references": [
        {
          "figure_number": "Figure 4",
          "panel": "",
          "figure_key": "figure_4"
        }
      ]
    },
    {
      "sentence": "The result of the post hoc analysis is reported in the upper diagonal of Fig. 3.",
      "figure_references": [
        {
          "figure_number": "Figure 3",
          "panel": "",
          "figure_key": "figure_3"
        }
      ]
    },
    {
      "sentence": "The result from the post hoc test is demonstrated in the lower diagonal of Fig. 3.Intra-Subregional Comparison Between the Acceptance of Receiving versus Giving Sugar Relationships (H3.3)\nWe compared the ASR-YWMS and ASR-OMWS in each subregion.",
      "figure_references": [
        {
          "figure_number": "Figure 3",
          "panel": "",
          "figure_key": "figure_3"
        }
      ]
    },
    {
      "sentence": "The comparison results are visualized in Fig. 4.",
      "figure_references": [
        {
          "figure_number": "Figure 4",
          "panel": "",
          "figure_key": "figure_4"
        }
      ]
    },
    {
      "sentence": "The result of the post hoc analysis is reported in the upper diagonal of Fig. 3.",
      "figure_references": [
        {
          "figure_number": "Figure 3",
          "panel": "",
          "figure_key": "figure_3"
        }
      ]
    },
    {
      "sentence": "The result from the post hoc test is demonstrated in the lower diagonal of Fig. 3.Intra-Subregional Comparison Between the Acceptance of Receiving versus Giving Sugar Relationships (H3.3)\nWe compared the ASR-YWMS and ASR-OMWS in each subregion.",
      "figure_references": [
        {
          "figure_number": "Figure 3",
          "panel": "",
          "figure_key": "figure_3"
        }
      ]
    },
    {
      "sentence": "The comparison results are visualized in Fig. 4.",
      "figure_references": [
        {
          "figure_number": "Figure 4",
          "panel": "",
          "figure_key": "figure_4"
        }
      ]
    },
    {
      "sentence": "The result of the post hoc analysis is reported in the upper diagonal of Fig. 3.",
      "figure_references": [
        {
          "figure_number": "Figure 3",
          "panel": "",
          "figure_key": "figure_3"
        }
      ]
    },
    {
      "sentence": "The result from the post hoc test is demonstrated in the lower diagonal of Fig. 3.Intra-Subregional Comparison Between the Acceptance of Receiving versus Giving Sugar Relationships (H3.3)\nWe compared the ASR-YWMS and ASR-OMWS in each subregion.",
      "figure_references": [
        {
          "figure_number": "Figure 3",
          "panel": "",
          "figure_key": "figure_3"
        }
      ]
    },
    {
      "sentence": "The comparison results are visualized in Fig. 4.",
      "figure_references": [
        {
          "figure_number": "Figure 4",
          "panel": "",
          "figure_key": "figure_4"
        }
      ]
    },
    {
      "sentence": "The result of the post hoc analysis is reported in the upper diagonal of Fig. 3.",
      "figure_references": [
        {
          "figure_number": "Figure 3",
          "panel": "",
          "figure_key": "figure_3"
        }
      ]
    },
    {
      "sentence": "The result from the post hoc test is demonstrated in the lower diagonal of Fig. 3.Intra-Subregional Comparison Between the Acceptance of Receiving versus Giving Sugar Relationships (H3.3)\nWe compared the ASR-YWMS and ASR-OMWS in each subregion.",
      "figure_references": [
        {
          "figure_number": "Figure 3",
          "panel": "",
          "figure_key": "figure_3"
        }
      ]
    },
    {
      "sentence": "The comparison results are visualized in Fig. 4.",
      "figure_references": [
        {
          "figure_number": "Figure 4",
          "panel": "",
          "figure_key": "figure_4"
        }
      ]
    },
    {
      "sentence": "The result of the post hoc analysis is reported in the upper diagonal of Fig. 3.",
      "figure_references": [
        {
          "figure_number": "Figure 3",
          "panel": "",
          "figure_key": "figure_3"
        }
      ]
    },
    {
      "sentence": "The result from the post hoc test is demonstrated in the lower diagonal of Fig. 3.Intra-Subregional Comparison Between the Acceptance of Receiving versus Giving Sugar Relationships (H3.3)\nWe compared the ASR-YWMS and ASR-OMWS in each subregion.",
      "figure_references": [
        {
          "figure_number": "Figure 3",
          "panel": "",
          "figure_key": "figure_3"
        }
      ]
    },
    {
      "sentence": "The comparison results are visualized in Fig. 4.",
      "figure_references": [
        {
          "figure_number": "Figure 4",
          "panel": "",
          "figure_key": "figure_4"
        }
      ]
    },
    {
      "sentence": "The result of the post hoc analysis is reported in the upper diagonal of Fig. 3.",
      "figure_references": [
        {
          "figure_number": "Figure 3",
          "panel": "",
          "figure_key": "figure_3"
        }
      ]
    },
    {
      "sentence": "The result from the post hoc test is demonstrated in the lower diagonal of Fig. 3.Intra-Subregional Comparison Between the Acceptance of Receiving versus Giving Sugar Relationships (H3.3)\nWe compared the ASR-YWMS and ASR-OMWS in each subregion.",
      "figure_references": [
        {
          "figure_number": "Figure 3",
          "panel": "",
          "figure_key": "figure_3"
        }
      ]
    },
    {
      "sentence": "The comparison results are visualized in Fig. 4.",
      "figure_references": [
        {
          "figure_number": "Figure 4",
          "panel": "",
          "figure_key": "figure_4"
        }
      ]
    },
    {
      "sentence": "The result of the post hoc analysis is reported in the upper diagonal of Fig. 3.",
      "figure_references": [
        {
          "figure_number": "Figure 3",
          "panel": "",
          "figure_key": "figure_3"
        }
      ]
    },
    {
      "sentence": "The result from the post hoc test is demonstrated in the lower diagonal of Fig. 3.Intra-Subregional Comparison Between the Acceptance of Receiving versus Giving Sugar Relationships (H3.3)\nWe compared the ASR-YWMS and ASR-OMWS in each subregion.",
      "figure_references": [
        {
          "figure_number": "Figure 3",
          "panel": "",
          "figure_key": "figure_3"
        }
      ]
    },
    {
      "sentence": "The comparison results are visualized in Fig. 4.",
      "figure_references": [
        {
          "figure_number": "Figure 4",
          "panel": "",
          "figure_key": "figure_4"
        }
      ]
    },
    {
      "sentence": "The result of the post hoc analysis is reported in the upper diagonal of Fig. 3.",
      "figure_references": [
        {
          "figure_number": "Figure 3",
          "panel": "",
          "figure_key": "figure_3"
        }
      ]
    },
    {
      "sentence": "The result from the post hoc test is demonstrated in the lower diagonal of Fig. 3.Intra-Subregional Comparison Between the Acceptance of Receiving versus Giving Sugar Relationships (H3.3)\nWe compared the ASR-YWMS and ASR-OMWS in each subregion.",
      "figure_references": [
        {
          "figure_number": "Figure 3",
          "panel": "",
          "figure_key": "figure_3"
        }
      ]
    },
    {
      "sentence": "The comparison results are visualized in Fig. 4.",
      "figure_references": [
        {
          "figure_number": "Figure 4",
          "panel": "",
          "figure_key": "figure_4"
        }
      ]
    },
    {
      "sentence": "The result of the post hoc analysis is reported in the upper diagonal of Fig. 3.",
      "figure_references": [
        {
          "figure_number": "Figure 3",
          "panel": "",
          "figure_key": "figure_3"
        }
      ]
    },
    {
      "sentence": "The result from the post hoc test is demonstrated in the lower diagonal of Fig. 3.",
      "figure_references": [
        {
          "figure_number": "Figure 3",
          "panel": "",
          "figure_key": "figure_3"
        }
      ]
    },
    {
      "sentence": "The result of the post hoc analysis is reported in the upper diagonal of Fig. 3.",
      "figure_references": [
        {
          "figure_number": "Figure 3",
          "panel": "",
          "figure_key": "figure_3"
        }
      ]
    },
    {
      "sentence": "The result from the post hoc test is demonstrated in the lower diagonal of Fig. 3.",
      "figure_references": [
        {
          "figure_number": "Figure 3",
          "panel": "",
          "figure_key": "figure_3"
        }
      ]
    },
    {
      "sentence": "The comparison results are visualized in Fig. 4.",
      "figure_references": [
        {
          "figure_number": "Figure 4",
          "panel": "",
          "figure_key": "figure_4"
        }
      ]
    },
    {
      "sentence": "The comparison results are visualized in Fig. 4.",
      "figure_references": [
        {
          "figure_number": "Figure 4",
          "panel": "",
          "figure_key": "figure_4"
        }
      ]
    }
  ],
  "extraction_stats": {
    "figures_count": 4,
    "claims_count": 33,
    "images_downloaded": 4,
    "tables_filtered": 318
  }
}